{
  "service_instances": 1,
  "storage_mock": true,
  "core_attest_url": "http://localhost:8088/attest",
  "core_api_token": "OPLCLAjLRWcVlCDl9+BbwR38gzxYdiWFa751ynWLuI7JU4iA=",
  "sites_metadata_path": "http://localhost:8088/sites/refresh",
  "clients_metadata_path": "http://localhost:8088/clients/refresh",
  "client_side_keypairs_metadata_path": "http://localhost:8088/client_side_keypairs/refresh",
  "keys_metadata_path": "http://localhost:8088/key/refresh",
  "keys_acl_metadata_path": "http://localhost:8088/key/acl/refresh",
  "keysets_metadata_path": "http://localhost:8088/key/keyset/refresh",
  "keyset_keys_metadata_path": "http://localhost:8088/key/keyset-keys/refresh",
  "salts_metadata_path": "http://localhost:8088/salt/refresh",
  "services_metadata_path": "http://localhost:8088/services/refresh",
  "service_links_metadata_path": "http://localhost:8088/service_links/refresh",
  "s3_keys_metadata_path": "https://core:8088/s3encryption_keys/retrieve",
  "identity_token_expires_after_seconds": 3600,
  "refresh_token_expires_after_seconds": 86400,
  "refresh_identity_token_after_seconds": 900,
  "advertising_token_v3": false,
  "refresh_token_v3": true,
  "identity_v3": false,
  "identity_scope": "uid2",
  "enable_v2_encryption": true,
  "sharing_token_expiry_seconds": 2592000,
  "cloud_download_threads": 8,
  "cloud_upload_threads": 2,
  "cloud_refresh_interval": 60,
  "optout_inmem_cache": false,
  "optout_synthetic_logs_enabled": false,
  "optout_data_dir": "/opt/uid2/operator-optout/",
  "optout_s3_folder": "optout/",
  "optout_bloom_filter_size": 8192,
  "optout_delta_rotate_interval": 300,
  "optout_delta_backtrack_in_days": 1,
  "optout_heap_default_capacity": 8192,
  "optout_max_partitions": 30,
  "optout_partition_interval": 86400,
  "client_side_token_generate": true,
  "client_side_token_generate_domain_name_check_enabled": false,
  "client_side_token_generate_log_invalid_http_origins": true,
  "salts_expired_shutdown_hours": 12
}
